regdurations/__init__.py
regdurations/languages.py
regdurations/py.typed
regdurations/regdurations.py
regdurations-1.0.7.dist-info/licenses/LICENSE_1_0.txt
regdurations-1.0.7.dist-info/METADATA
regdurations-1.0.7.dist-info/WHEEL
regdurations-1.0.7.dist-info/top_level.txt
regdurations-1.0.7.dist-info/RECORD
