Metadata-Version: 2.4
Name: regdurations
Version: 1.0.7
Summary: Parse user-provided duration strings using regular expressions
Author: CrisMystik
License-Expression: BSL-1.0
Project-URL: Homepage, https://github.com/CrisMystik/RegDurations
Project-URL: Issues, https://github.com/CrisMystik/RegDurations/issues
Classifier: Programming Language :: Python :: 3
Classifier: Operating System :: OS Independent
Classifier: Typing :: Typed
Classifier: Intended Audience :: Developers
Classifier: Development Status :: 5 - Production/Stable
Classifier: Natural Language :: English
Classifier: Natural Language :: Italian
Classifier: Natural Language :: French
Classifier: Natural Language :: Spanish
Classifier: Natural Language :: German
Requires-Python: >=3.9
License-File: LICENSE_1_0.txt
Provides-Extra: find-relativedelta
Requires-Dist: python-dateutil; extra == "find-relativedelta"
Dynamic: license-file
